{
    "name": "Base16 Solar Flare",
    "foreground": "#A6AFB8",
    "background": "#18262F",
    "cursorColor": "#A6AFB8",
    "selectionBackground": "#586875",
    "black": "#18262F",
    "red": "#EF5253",
    "green": "#7CC844",
    "yellow": "#E4B51C",
    "blue": "#33B5E1",
    "purple": "#A363D5",
    "cyan": "#52CBB0",
    "white": "#A6AFB8",
    "brightBlack": "#667581",
    "brightRed": "#E66B2B",
    "brightGreen": "#222E38",
    "brightYellow": "#586875",
    "brightBlue": "#85939E",
    "brightPurple": "#E8E9ED",
    "brightCyan": "#D73C9A",
    "brightWhite": "#F5F7FA"
}
